{
"skeleton": {
	"hash": "YOMBebFY7veDEXgEZPaM5d+rFYY",
	"spine": "3.8.75",
	"x": -59.84,
	"y": -0.59,
	"width": 123.65,
	"height": 180.21,
	"images": "./images/",
	"audio": "C:/Users/kyltu/OneDrive/Рабочий стол/Fantasy Quest"
},
"bones": [
	{ "name": "root", "x": 1.99, "y": 0.78 },
	{ "name": "bone", "parent": "root", "length": 10.01, "rotation": -91.61, "x": -2.25, "y": 44.53 },
	{ "name": "bone2", "parent": "bone", "length": 28.48, "rotation": -178.95, "x": -2.39, "y": -0.21 },
	{ "name": "bone3", "parent": "bone2", "length": 58.14, "rotation": 2.79, "x": 27.35, "y": 0.55 },
	{ "name": "bone4", "parent": "bone3", "length": 30.22, "rotation": -30.34, "x": -26.13, "y": -0.54 },
	{ "name": "bone6", "parent": "bone2", "length": 31.62, "rotation": 24.5, "x": 0.82, "y": 3.11 },
	{ "name": "bone8", "parent": "bone", "length": 22.56, "rotation": -7.38, "x": -1.89, "y": -7.95 },
	{ "name": "bone9", "parent": "bone8", "length": 22.65, "rotation": 2.91, "x": 22.51, "y": 0.28 },
	{ "name": "bone10", "parent": "bone", "length": 22.97, "rotation": 7.6, "x": -2.81, "y": 9.51 },
	{ "name": "bone11", "parent": "bone10", "length": 24.86, "rotation": -2.41, "x": 22.47, "y": 0.62 },
	{ "name": "bone12", "parent": "bone3", "length": 48.46, "rotation": -25.47, "x": 55.81, "y": 0.91 },
	{ "name": "bone5", "parent": "bone4", "length": 18.17, "rotation": -113.08, "x": 30.39, "y": -0.37 },
	{ "name": "bone7", "parent": "bone5", "length": 22.58, "rotation": -33.61, "x": 18.17 },
	{ "name": "bone13", "parent": "bone6", "length": 15.82, "rotation": 132.1, "x": 31.45, "y": 0.21 },
	{ "name": "bone14", "parent": "bone13", "length": 22.42, "rotation": -5.27, "x": 18.75, "y": -0.13 },
	{ "name": "bone15", "parent": "bone3", "length": 50.05, "rotation": 1.83, "x": 16.57, "y": 92.61 }
],
"slots": [
	{ "name": "Left arm", "bone": "root", "attachment": "Left arm" },
	{ "name": "Left leg", "bone": "root", "attachment": "Left leg" },
	{ "name": "Right leg", "bone": "root", "attachment": "Right leg" },
	{ "name": "Body", "bone": "root", "attachment": "Body" },
	{ "name": "Right arm", "bone": "root", "attachment": "Right arm" },
	{ "name": "Head", "bone": "root", "attachment": "Head" },
	{ "name": "Hair", "bone": "root", "attachment": "Hair" },
	{ "name": "Hat", "bone": "root", "attachment": "Hat" }
],
"skins": [
	{
		"name": "default",
		"attachments": {
			"Head": {
				"Head": {
					"type": "mesh",
					"uvs": [ 0.36191, 0.01295, 0.62263, 0.01367, 0.77153, 0.08299, 0.9043, 0.21108, 0.95801, 0.35459, 0.95591, 0.5784, 0.98589, 0.61621, 0.98578, 0.7124, 0.90359, 0.79011, 0.84634, 0.80361, 0.76716, 0.87782, 0.59387, 0.9592, 0.39533, 0.99686, 0.24907, 0.95103, 0.15815, 0.89002, 0.05549, 0.79229, 0.01412, 0.52041, 0.01433, 0.30036, 0.07224, 0.19142, 0.21001, 0.06158, 0.35009, 0.87115, 0.34396, 0.59494, 0.36644, 0.37861, 0.40935, 0.23182 ],
					"triangles": [ 13, 20, 12, 12, 20, 11, 10, 11, 21, 13, 14, 20, 20, 14, 21, 9, 10, 21, 14, 15, 21, 21, 11, 20, 8, 9, 5, 15, 16, 21, 5, 9, 21, 5, 21, 22, 2, 5, 22, 8, 5, 7, 4, 5, 2, 23, 2, 22, 7, 5, 6, 23, 1, 2, 21, 16, 22, 4, 2, 3, 16, 17, 22, 17, 18, 22, 22, 18, 23, 23, 18, 19, 19, 0, 23, 23, 0, 1 ],
					"vertices": [ 2, 3, 68.78, 3.97, 0.77, 15, 52.98, -89.83, 0.23, 2, 3, 68.03, -14.01, 0.85, 15, 51.61, -107.77, 0.15, 2, 3, 62.57, -24.08, 0.85, 15, 45.81, -117.64, 0.15, 2, 3, 52.87, -32.87, 0.85, 15, 35.81, -126.09, 0.15, 2, 3, 42.26, -36.16, 0.85, 15, 25.09, -129.02, 0.15, 2, 3, 25.94, -35.38, 0.85, 15, 8.81, -127.68, 0.15, 2, 3, 23.1, -37.34, 0.85, 15, 5.9, -129.54, 0.15, 2, 3, 16.08, -37.07, 0.85, 15, -1.1, -129.02, 0.15, 2, 3, 10.64, -31.18, 0.85, 15, -6.34, -122.95, 0.15, 2, 3, 9.8, -27.19, 0.85, 15, -7.03, -118.94, 0.15, 2, 3, 4.6, -21.52, 0.85, 15, -12.04, -113.09, 0.15, 2, 3, -0.87, -9.34, 0.85, 15, -17.08, -100.73, 0.15, 2, 3, -3.08, 4.45, 0.62, 15, -18.82, -86.87, 0.38, 2, 3, 0.65, 14.41, 0.77, 15, -14.75, -77.05, 0.23, 2, 3, 5.34, 20.5, 0.77, 15, -9.85, -71.12, 0.23, 2, 3, 12.75, 27.3, 0.77, 15, -2.21, -64.58, 0.23, 2, 3, 32.69, 29.38, 0.77, 15, 17.79, -63.18, 0.23, 2, 3, 48.74, 28.75, 0.77, 15, 33.81, -64.37, 0.23, 2, 3, 56.53, 24.45, 0.77, 15, 41.45, -68.94, 0.23, 2, 3, 65.64, 14.58, 0.77, 15, 50.21, -79.12, 0.23, 2, 3, 6.21, 7.21, 0.62, 15, -9.44, -84.43, 0.38, 2, 3, 26.37, 6.85, 0.62, 15, 10.7, -85.48, 0.38, 2, 3, 42.09, 4.69, 0.62, 15, 26.33, -88.19, 0.38, 2, 3, 52.68, 1.32, 0.62, 15, 36.8, -91.92, 0.38 ],
					"hull": 20,
					"edges": [ 0, 38, 0, 2, 2, 4, 4, 6, 6, 8, 8, 10, 10, 12, 12, 14, 14, 16, 16, 18, 18, 20, 20, 22, 22, 24, 24, 26, 26, 28, 28, 30, 30, 32, 32, 34, 34, 36, 36, 38, 24, 40, 40, 42, 42, 44, 44, 46, 46, 2 ],
					"width": 69,
					"height": 73
				}
			},
			"Body": {
				"Body": {
					"type": "mesh",
					"uvs": [ 0.4963, 0.03538, 0.60748, 0.04126, 0.73181, 0.04683, 0.85561, 0.13119, 0.97248, 0.37225, 0.93083, 0.71144, 0.97758, 0.76188, 0.97692, 0.84552, 0.74859, 0.96227, 0.51174, 0.98573, 0.42749, 0.95228, 0.2354, 0.95436, 0.07731, 0.87319, 0.03821, 0.79377, 0.06933, 0.66677, 0.02265, 0.57091, 0.02269, 0.40406, 0.11918, 0.17544, 0.25612, 0.0708, 0.37749, 0.7509, 0.36437, 0.51926, 0.40044, 0.29433 ],
					"triangles": [ 21, 18, 0, 17, 18, 21, 21, 16, 17, 20, 16, 21, 15, 16, 20, 14, 15, 20, 4, 21, 3, 5, 19, 20, 14, 20, 19, 21, 0, 1, 3, 21, 1, 3, 1, 2, 4, 20, 21, 12, 13, 14, 7, 5, 6, 19, 12, 14, 20, 4, 5, 5, 8, 19, 19, 9, 10, 11, 12, 19, 10, 11, 19, 7, 8, 5, 8, 9, 19 ],
					"vertices": [ 1, 2, 37.41, -2.08, 1, 1, 2, 37.21, -6.87, 1, 1, 2, 37.03, -12.21, 1, 1, 2, 33.54, -17.57, 1, 1, 2, 23.46, -22.7, 1, 1, 2, 9.2, -21.05, 1, 1, 2, 7.1, -23.08, 1, 1, 2, 3.59, -23.09, 1, 1, 2, -1.41, -13.32, 1, 1, 2, -2.5, -3.14, 1, 1, 2, -1.13, 0.49, 1, 1, 2, -1.3, 8.75, 1, 1, 2, 2.04, 15.58, 1, 1, 2, 5.36, 17.3, 1, 1, 2, 10.71, 16.01, 1, 1, 2, 14.71, 18.06, 1, 1, 2, 21.72, 18.13, 1, 1, 2, 31.36, 14.07, 1, 1, 2, 35.82, 8.23, 1, 1, 2, 7.31, 2.73, 1, 1, 2, 17.03, 3.39, 1, 1, 2, 26.49, 1.93, 1 ],
					"hull": 19,
					"edges": [ 0, 36, 0, 2, 2, 4, 4, 6, 6, 8, 8, 10, 10, 12, 12, 14, 14, 16, 16, 18, 18, 20, 20, 22, 22, 24, 24, 26, 26, 28, 28, 30, 30, 32, 32, 34, 34, 36, 20, 38, 38, 40, 40, 42, 42, 0 ],
					"width": 43,
					"height": 42
				}
			},
			"Hair": {
				"Hair": {
					"type": "mesh",
					"uvs": [ 0.55515, 0.02279, 0.55527, 0.02097, 0.62393, 0.0573, 0.73905, 0.05732, 0.82381, 0.08581, 0.92939, 0.19218, 0.98892, 0.3024, 0.98881, 0.59842, 0.94761, 0.76434, 0.83496, 0.91686, 0.69305, 0.98911, 0.64544, 0.9892, 0.73815, 0.81448, 0.78367, 0.6646, 0.78354, 0.4944, 0.63524, 0.55485, 0.63659, 0.48477, 0.48963, 0.59915, 0.4031, 0.51216, 0.28446, 0.56241, 0.32009, 0.77487, 0.38238, 0.94838, 0.26292, 0.89917, 0.14979, 0.74617, 0.11322, 0.61479, 0.11351, 0.40328, 0.05637, 0.54321, 0.01124, 0.54038, 0.01106, 0.37674, 0.06217, 0.27625, 0.2266, 0.14761, 0.29611, 0.07999, 0.40915, 0.02265 ],
					"triangles": [ 0, 1, 2, 25, 29, 30, 28, 29, 25, 16, 2, 3, 16, 3, 4, 14, 16, 4, 5, 14, 4, 6, 14, 5, 18, 31, 32, 30, 31, 18, 25, 30, 18, 2, 18, 32, 2, 32, 0, 18, 2, 16, 26, 27, 28, 25, 26, 28, 16, 17, 18, 15, 16, 14, 19, 25, 18, 7, 14, 6, 19, 24, 25, 13, 14, 7, 23, 24, 19, 8, 13, 7, 23, 19, 20, 12, 13, 8, 22, 23, 20, 9, 12, 8, 22, 20, 21, 10, 12, 9, 10, 11, 12 ],
					"vertices": [ 1, 3, 74.55, -1.14, 1, 1, 3, 74.7, -1.16, 1, 1, 3, 71.31, -7.07, 1, 1, 3, 70.92, -17.2, 1, 1, 3, 68.15, -24.55, 1, 1, 3, 58.54, -33.48, 1, 1, 3, 48.76, -38.34, 1, 1, 3, 23.02, -37.33, 1, 1, 3, 8.74, -33.15, 1, 1, 3, -4.14, -22.73, 1, 1, 3, -9.93, -10, 1, 1, 3, -9.78, -5.82, 1, 1, 3, 5.09, -14.56, 1, 1, 3, 17.97, -19.07, 1, 1, 3, 32.77, -19.63, 1, 1, 3, 28.02, -6.39, 1, 1, 3, 34.11, -6.74, 1, 1, 3, 24.66, 6.57, 1, 1, 3, 32.52, 13.88, 1, 1, 3, 28.56, 24.48, 1, 1, 3, 9.97, 22.07, 1, 1, 3, -5.33, 17.18, 1, 1, 3, -0.64, 27.51, 1, 1, 3, 13.04, 36.95, 1, 1, 3, 24.59, 39.72, 1, 1, 3, 42.98, 38.98, 1, 1, 3, 31.01, 44.48, 1, 1, 3, 31.41, 48.43, 1, 1, 3, 45.63, 47.9, 1, 1, 3, 54.19, 43.06, 1, 1, 3, 64.82, 28.17, 1, 1, 3, 70.46, 21.83, 1, 1, 3, 75.06, 11.7, 1 ],
					"hull": 33,
					"edges": [ 0, 64, 0, 2, 2, 4, 4, 6, 6, 8, 8, 10, 10, 12, 12, 14, 14, 16, 16, 18, 18, 20, 20, 22, 22, 24, 24, 26, 26, 28, 28, 30, 30, 32, 32, 34, 34, 36, 36, 38, 38, 40, 40, 42, 42, 44, 44, 46, 46, 48, 48, 50, 50, 52, 52, 54, 54, 56, 56, 58, 58, 60, 60, 62, 62, 64 ],
					"width": 88,
					"height": 87
				}
			},
			"Left leg": {
				"Left leg": {
					"type": "mesh",
					"uvs": [ 0.32614, 0.00749, 0.96993, 0.10253, 0.97208, 0.23594, 0.92094, 0.34432, 0.69805, 0.6066, 0.69733, 0.75042, 0.63673, 0.76813, 0.56694, 0.93324, 0.48822, 0.98265, 0.24158, 0.98253, 0.15731, 0.95715, 0.11774, 0.90746, 0.15105, 0.75003, 0.04267, 0.68611, 0.08037, 0.63021, 0.15117, 0.58932, 0.15097, 0.52731, 0.03009, 0.34811, 0.02858, 0.21684, 0.14699, 0.10944, 0.32032, 0.00729 ],
					"triangles": [ 12, 14, 15, 6, 12, 15, 13, 14, 12, 15, 4, 6, 5, 6, 4, 7, 12, 6, 9, 11, 12, 9, 10, 11, 12, 7, 9, 8, 9, 7, 2, 3, 0, 2, 0, 1, 17, 18, 19, 17, 19, 3, 16, 17, 3, 0, 19, 20, 3, 19, 0, 4, 15, 16, 3, 4, 16 ],
					"vertices": [ 1, 6, -8.93, -5.84, 1, 2, 6, -6.99, 15.98, 0.99192, 7, -29.29, 16.09, 0.00808, 2, 6, 0.38, 17.22, 0.95961, 7, -21.91, 17.23, 0.04039, 2, 6, 6.63, 16.5, 0.87869, 7, -15.66, 16.43, 0.12131, 2, 6, 22.29, 11.53, 0.09781, 7, -0.07, 11.25, 0.90219, 1, 7, 7.9, 12.38, 1, 1, 7, 9.17, 10.54, 1, 1, 7, 18.65, 9.59, 1, 1, 7, 21.76, 7.41, 1, 1, 7, 22.92, -0.64, 1, 1, 7, 21.91, -3.6, 1, 1, 7, 19.34, -5.29, 1, 2, 6, 33.04, -5.05, 0.07339, 7, 10.46, -5.46, 0.92661, 2, 6, 30.07, -9.14, 0.27045, 7, 7.43, -9.52, 0.72955, 2, 6, 26.78, -8.4, 0.38863, 7, 4.16, -8.73, 0.61137, 2, 6, 24.15, -6.45, 0.67112, 7, 1.55, -6.75, 0.32888, 2, 6, 20.73, -7, 0.97554, 7, -1.88, -7.25, 0.02446, 1, 6, 11.44, -12.51, 1, 1, 6, 4.18, -13.7, 1, 1, 6, -2.37, -10.78, 1, 1, 6, -8.91, -6.03, 1 ],
					"hull": 21,
					"edges": [ 0, 40, 0, 2, 2, 4, 4, 6, 6, 8, 8, 10, 10, 12, 12, 14, 14, 16, 16, 18, 18, 20, 20, 22, 22, 24, 24, 26, 26, 28, 28, 30, 30, 32, 32, 34, 34, 36, 36, 38, 38, 40 ],
					"width": 33,
					"height": 56
				}
			},
			"Left arm": {
				"Left arm": {
					"type": "mesh",
					"uvs": [ 0.75849, 0.02392, 0.85416, 0.05647, 0.87473, 0.06324, 0.90635, 0.0848, 0.97049, 0.15032, 0.96919, 0.15447, 0.96921, 0.27821, 0.9731, 0.29001, 0.9376, 0.36222, 0.72064, 0.61527, 0.69331, 0.64598, 0.67484, 0.67581, 0.65684, 0.70301, 0.65657, 0.77139, 0.65675, 0.87372, 0.65418, 0.87576, 0.59465, 0.9568, 0.59839, 0.95624, 0.53118, 0.979, 0.46855, 0.97899, 0.43592, 0.96779, 0.40661, 0.95804, 0.31255, 0.89407, 0.28484, 0.90014, 0.18145, 0.92364, 0.13101, 0.90661, 0.09372, 0.89394, 0.06219, 0.87257, 0.03071, 0.82959, 0.03086, 0.82138, 0.03091, 0.76584, 0.09352, 0.55286, 0.21724, 0.40562, 0.2543, 0.33091, 0.30523, 0.22539, 0.32895, 0.17996, 0.51474, 0.05348, 0.52773, 0.04309, 0.62438, 0.02106, 0.75394, 0.02106 ],
					"triangles": [ 32, 33, 9, 10, 31, 32, 9, 10, 32, 11, 31, 10, 12, 31, 11, 30, 31, 12, 13, 30, 12, 26, 27, 29, 29, 30, 26, 28, 29, 27, 30, 13, 26, 14, 15, 13, 13, 22, 26, 15, 22, 13, 23, 26, 22, 25, 26, 23, 24, 25, 23, 22, 15, 21, 15, 20, 21, 16, 20, 15, 18, 19, 20, 16, 18, 20, 18, 16, 17, 5, 3, 4, 1, 5, 6, 5, 1, 3, 8, 6, 7, 37, 38, 36, 0, 38, 39, 1, 38, 0, 38, 1, 8, 3, 1, 2, 1, 6, 8, 38, 8, 36, 8, 35, 36, 8, 34, 35, 8, 33, 34, 9, 33, 8 ],
					"vertices": [ 1, 13, -3.96, 0.91, 1, 1, 13, -3.8, 4.33, 1, 1, 13, -3.78, 5.06, 1, 1, 13, -3.26, 6.4, 1, 1, 13, -1.28, 9.52, 1, 1, 13, -1.09, 9.56, 1, 2, 13, 4.23, 11.93, 0.996, 14, -15.57, 10.67, 0.004, 2, 13, 4.68, 12.27, 0.99438, 14, -15.15, 11.05, 0.00562, 2, 13, 8.25, 12.61, 0.96509, 14, -11.63, 11.72, 0.03491, 2, 13, 21.93, 11.09, 0.21852, 14, 2.14, 11.47, 0.78148, 2, 13, 23.61, 10.88, 0.13027, 14, 3.82, 11.41, 0.86973, 2, 13, 25.13, 10.91, 0.0731, 14, 5.34, 11.58, 0.9269, 2, 13, 26.53, 10.9, 0.03657, 14, 6.73, 11.7, 0.96343, 2, 13, 29.47, 12.2, 0.00423, 14, 9.54, 13.27, 0.99577, 2, 13, 33.86, 14.16, 0, 14, 13.73, 15.62, 1, 2, 13, 33.99, 14.12, 0, 14, 13.86, 15.59, 1, 2, 13, 38.24, 13.93, 0, 14, 18.11, 15.79, 1, 2, 13, 38.17, 14.03, 0, 14, 18.03, 15.88, 1, 2, 13, 40.02, 12.5, 0, 14, 20.02, 14.53, 1, 2, 13, 40.83, 10.66, 0, 14, 20.99, 12.78, 1, 2, 13, 40.77, 9.5, 0, 14, 21.04, 11.61, 1, 2, 13, 40.74, 8.45, 0, 14, 21.1, 10.57, 1, 1, 14, 19.95, 6.48, 1, 1, 14, 20.63, 5.84, 1, 1, 14, 23.21, 3.49, 1, 1, 14, 23.3, 1.69, 1, 1, 14, 23.36, 0.36, 1, 2, 13, 41.54, -3.25, 0, 14, 22.98, -1.01, 1, 2, 13, 40.11, -4.99, 0, 14, 21.71, -2.87, 1, 2, 13, 39.75, -5.14, 0, 14, 21.37, -3.06, 1, 2, 13, 37.37, -6.2, 0, 14, 19.09, -4.33, 1, 2, 13, 27.4, -8.44, 1.0E-5, 14, 9.38, -7.47, 0.99999, 2, 13, 19.47, -7.63, 0.25106, 14, 1.41, -7.4, 0.74894, 2, 13, 15.78, -7.97, 0.65536, 14, -2.24, -8.08, 0.34464, 2, 13, 10.59, -8.5, 0.96264, 14, -7.36, -9.08, 0.03736, 2, 13, 8.33, -8.67, 0.9922, 14, -9.6, -9.46, 0.0078, 1, 13, 0.48, -5.65, 1, 1, 13, -0.13, -5.47, 1, 1, 13, -2.34, -3.06, 1, 1, 13, -4.02, 0.72, 1 ],
					"hull": 40,
					"edges": [ 0, 78, 0, 2, 2, 4, 4, 6, 6, 8, 8, 10, 10, 12, 12, 14, 14, 16, 16, 18, 18, 20, 20, 22, 22, 24, 24, 26, 26, 28, 28, 30, 30, 32, 32, 34, 34, 36, 36, 38, 38, 40, 40, 42, 42, 44, 44, 46, 46, 48, 48, 50, 50, 52, 52, 54, 54, 56, 56, 58, 58, 60, 60, 62, 62, 64, 64, 66, 66, 68, 68, 70, 70, 72, 72, 74, 74, 76, 76, 78 ],
					"width": 32,
					"height": 47
				}
			},
			"Right leg": {
				"Right leg": {
					"type": "mesh",
					"uvs": [ 0.3237, 0.01599, 0.61367, 0.01625, 0.80644, 0.11439, 0.90064, 0.18235, 0.98473, 0.29471, 0.87319, 0.52071, 0.8713, 0.57073, 0.9359, 0.64162, 0.93599, 0.7051, 0.8714, 0.70622, 0.87151, 0.91841, 0.77369, 0.96752, 0.47476, 0.96744, 0.39669, 0.92247, 0.32213, 0.77058, 0.22513, 0.73774, 0.22474, 0.68922, 0.25709, 0.61899, 0.06416, 0.42968, 0.06366, 0.05695, 0.17464, 0.02926 ],
					"triangles": [ 6, 17, 5, 9, 6, 7, 9, 7, 8, 17, 6, 9, 14, 16, 17, 14, 15, 16, 17, 9, 14, 13, 14, 9, 10, 13, 9, 11, 12, 13, 10, 11, 13, 18, 19, 20, 3, 18, 2, 4, 18, 3, 5, 18, 4, 0, 18, 20, 17, 18, 5, 0, 2, 18, 1, 2, 0 ],
					"vertices": [ 1, 8, -10.02, -3.56, 1, 1, 8, -9.07, 5.38, 1, 2, 8, -2.49, 10.7, 0.99068, 9, -25.36, 9.02, 0.00932, 2, 8, 1.93, 13.17, 0.96111, 9, -21.04, 11.68, 0.03889, 2, 8, 9.02, 15.05, 0.86351, 9, -14.04, 13.85, 0.13649, 2, 8, 22.37, 10.17, 0.15574, 9, -0.5, 9.54, 0.84426, 2, 8, 25.4, 9.8, 0.02395, 9, 2.55, 9.29, 0.97605, 1, 9, 6.99, 11.02, 1, 1, 9, 10.85, 10.78, 1, 1, 9, 10.8, 8.78, 1, 1, 9, 23.71, 7.98, 1, 1, 9, 26.51, 4.76, 1, 1, 9, 25.93, -4.49, 1, 2, 8, 45.2, -7.08, 3.1E-4, 9, 23.04, -6.73, 0.99969, 2, 8, 35.75, -8.41, 0.11334, 9, 13.65, -8.46, 0.88666, 2, 8, 33.44, -11.19, 0.22447, 9, 11.46, -11.34, 0.77553, 2, 8, 30.5, -10.89, 0.31148, 9, 8.51, -11.16, 0.68852, 2, 8, 26.34, -9.45, 0.62827, 9, 4.3, -9.9, 0.37173, 1, 8, 14.23, -14.19, 1, 1, 8, -8.38, -11.83, 1, 1, 8, -9.7, -8.24, 1 ],
					"hull": 21,
					"edges": [ 0, 40, 0, 2, 2, 4, 4, 6, 6, 8, 8, 10, 10, 12, 12, 14, 14, 16, 16, 18, 18, 20, 20, 22, 22, 24, 24, 26, 26, 28, 28, 30, 30, 32, 32, 34, 34, 36, 36, 38, 38, 40 ],
					"width": 31,
					"height": 61
				}
			},
			"Right arm": {
				"Right arm": {
					"type": "mesh",
					"uvs": [ 0.19275, 0.01856, 0.35485, 0.01846, 0.48314, 0.05582, 0.71467, 0.19126, 0.91349, 0.38895, 0.96819, 0.54547, 0.96833, 0.62302, 0.93589, 0.68116, 0.93584, 0.75483, 0.85432, 0.89847, 0.70932, 0.98122, 0.51626, 0.98211, 0.45239, 0.9458, 0.14161, 0.40031, 0.03183, 0.26528, 0.03175, 0.09568, 0.12037, 0.03985 ],
					"triangles": [ 5, 12, 4, 7, 5, 6, 7, 12, 5, 8, 9, 7, 9, 12, 7, 4, 12, 13, 10, 12, 9, 11, 12, 10, 14, 15, 16, 0, 14, 16, 3, 13, 14, 13, 3, 4, 0, 2, 3, 2, 0, 1, 0, 3, 14 ],
					"vertices": [ 1, 11, -3.16, 4.04, 1, 1, 11, -0.01, 7.96, 1, 1, 11, 4.02, 9.82, 1, 2, 11, 14.12, 10.91, 0.90684, 12, -9.42, 6.84, 0.09316, 2, 11, 26.14, 9.15, 0.15353, 12, 1.57, 12.03, 0.84647, 2, 11, 33.67, 5.27, 0.00145, 12, 9.99, 12.97, 0.99855, 1, 12, 14.08, 12.6, 1, 1, 12, 17.06, 11.32, 1, 1, 12, 20.95, 10.97, 1, 1, 12, 28.3, 7.76, 1, 1, 12, 32.26, 2.89, 1, 1, 12, 31.77, -3.08, 1, 1, 12, 29.67, -4.88, 1, 2, 11, 11.62, -9.88, 0.81414, 12, 0.01, -11.85, 0.18586, 2, 11, 3.91, -8.04, 0.99783, 12, -7.43, -14.59, 0.00217, 1, 11, -3.1, -2.41, 1, 1, 11, -3.68, 1.58, 1 ],
					"hull": 17,
					"edges": [ 0, 32, 0, 2, 2, 4, 4, 6, 6, 8, 8, 10, 10, 12, 12, 14, 14, 16, 16, 18, 18, 20, 20, 22, 22, 24, 24, 26, 26, 28, 28, 30, 30, 32 ],
					"width": 31,
					"height": 53
				}
			},
			"Hat": {
				"Hat": {
					"type": "mesh",
					"uvs": [ 0.59655, 0.01324, 0.80947, 0.11876, 0.82437, 0.11979, 0.96041, 0.11966, 0.96007, 0.21443, 0.86493, 0.29248, 0.72865, 0.3352, 0.76731, 0.59198, 0.99282, 0.78769, 0.9921, 0.86687, 0.94401, 0.94759, 0.8715, 0.98681, 0.73294, 0.9869, 0.65476, 0.9526, 0.48013, 0.80703, 0.41425, 0.77259, 0.30406, 0.74741, 0.15214, 0.74687, 0.08778, 0.69352, 0.02765, 0.59313, 0.00363, 0.47232, 0.02045, 0.42633, 0.16168, 0.42645, 0.25703, 0.39257, 0.34357, 0.20021, 0.43267, 0.05186, 0.47945, 0.0128 ],
					"triangles": [ 4, 2, 3, 5, 2, 4, 6, 0, 1, 5, 6, 1, 5, 1, 2, 19, 21, 22, 20, 21, 19, 18, 19, 22, 17, 18, 22, 15, 16, 23, 22, 23, 16, 17, 22, 16, 24, 14, 15, 15, 23, 24, 25, 26, 0, 25, 0, 6, 6, 24, 25, 6, 14, 24, 14, 6, 7, 7, 8, 11, 9, 10, 8, 13, 14, 7, 7, 12, 13, 8, 10, 11, 11, 12, 7 ],
					"vertices": [ 1, 10, 51.95, 2.69, 1, 1, 10, 55.18, -24.89, 1, 1, 10, 55.85, -26.63, 1, 1, 10, 62.57, -42.25, 1, 1, 10, 56.02, -45.02, 1, 1, 10, 45.95, -36.4, 1, 1, 10, 36.28, -22.02, 1, 1, 10, 20.49, -34.06, 1, 1, 10, 18.13, -65.75, 1, 1, 10, 12.64, -68.01, 1, 1, 10, 4.7, -64.88, 1, 1, 10, -1.58, -57.71, 1, 1, 10, -8.42, -41.8, 1, 1, 10, -9.91, -31.8, 1, 1, 10, -8.49, -7.44, 1, 1, 10, -9.37, 1.15, 1, 1, 10, -13.07, 14.55, 1, 1, 10, -20.53, 32.01, 1, 1, 10, -20.03, 40.99, 1, 1, 10, -16.08, 50.86, 1, 1, 10, -8.93, 57.2, 1, 1, 10, -4.94, 56.63, 1, 1, 10, 2.02, 40.4, 1, 1, 10, 9.06, 30.45, 1, 1, 10, 26.59, 26.21, 1, 1, 10, 41.2, 20.36, 1, 1, 10, 46.2, 16.15, 1 ],
					"hull": 27,
					"edges": [ 0, 52, 0, 2, 2, 4, 4, 6, 6, 8, 8, 10, 10, 12, 12, 14, 14, 16, 16, 18, 18, 20, 20, 22, 22, 24, 24, 26, 26, 28, 28, 30, 30, 32, 32, 34, 34, 36, 36, 38, 38, 40, 40, 42, 42, 44, 44, 46, 46, 48, 48, 50, 50, 52 ],
					"width": 125,
					"height": 75
				}
			}
		}
	}
],
"animations": {
	"Idle": {
		"bones": {
			"root": {
				"translate": [
					{ "x": -1.99, "y": -0.78 }
				]
			},
			"bone15": {
				"translate": [
					{ "x": -0.49, "y": 0.02 },
					{ "time": 0.6667, "x": -7.9, "y": 0.31 },
					{ "time": 1.3333, "x": -0.49, "y": 0.02 }
				]
			},
			"bone": {
				"translate": [
					{},
					{ "time": 0.6667, "y": -1.73 },
					{ "time": 1.3333 }
				]
			},
			"bone8": {
				"rotate": [
					{},
					{ "time": 0.6667, "angle": -4.19 },
					{ "time": 1.3333 }
				]
			},
			"bone9": {
				"rotate": [
					{},
					{ "time": 0.6667, "angle": 15.54 },
					{ "time": 1.3333 }
				]
			},
			"bone10": {
				"rotate": [
					{},
					{ "time": 0.6667, "angle": -5.32 },
					{ "time": 1.3333 }
				]
			},
			"bone11": {
				"rotate": [
					{},
					{ "time": 0.6667, "angle": 5.29 },
					{ "time": 1.3333 }
				]
			}
		}
	},
	"Walk": {
		"bones": {
			"root": {
				"translate": [
					{ "x": -1.99, "y": -0.78 }
				]
			},
			"bone8": {
				"rotate": [
					{ "angle": -38.54 },
					{ "time": 0.6667, "angle": 0.94 },
					{ "time": 1.3333, "angle": -25.35 },
					{ "time": 2, "angle": -38.54 }
				]
			},
			"bone9": {
				"rotate": [
					{ "angle": 38.53 },
					{ "time": 0.6667, "angle": 55.08 },
					{ "time": 1.3333, "angle": 31.36 },
					{ "time": 2, "angle": 38.53 }
				]
			},
			"bone10": {
				"rotate": [
					{ "angle": 13.2 },
					{ "time": 0.6667, "angle": -18.78 },
					{ "time": 1.3333, "angle": -0.66 },
					{ "time": 2, "angle": 13.2 }
				]
			},
			"bone11": {
				"rotate": [
					{ "angle": 22.45 },
					{ "time": 0.6667, "angle": 34.45 },
					{ "time": 1.3333, "angle": 12.03 },
					{ "time": 2, "angle": 22.45 }
				]
			},
			"bone15": {
				"translate": [
					{},
					{ "time": 1, "x": -12.28, "y": -2.33 },
					{ "time": 2, "x": -0.49, "y": 0.02 }
				]
			}
		}
	}
}
}